{
  "_comment": "12 ensaios ficticios",
  "EnsaiosFicticios": [
    {
      "id": 1,
      "maiorPremioEstaNoBotaoDireito": false,
      "_comment1": "valor em moedas do prêmio imediato",
      "valorPremioImediato": 700,
      "_comment2": "pontuação ao escolher o prêmio imediato",
      "pontuacaoPremioImediato": 700,
      "_comment3": "valor em moedas do segundo prêmio",
      "valorSegundoPremio": 1000,
      "_comment4": "tempo em segundos do segundo prêmio",
      "tempoSegundoPremio": 15,
      "_comment5": "pontuação ao escolher o segundo prêmio",
      "pontuacaoSegundoPremio": 1000
    },
    {
      "id": 2,
      "maiorPremioEstaNoBotaoDireito": true,
      "valorPremioImediato": 100,
      "pontuacaoPremioImediato": 100,
      "valorSegundoPremio": 1000,
      "tempoSegundoPremio": 60,
      "pontuacaoSegundoPremio": 1000
    },
    {
      "id": 3,
      "maiorPremioEstaNoBotaoDireito": false,
      "valorPremioImediato": 300,
      "pontuacaoPremioImediato": 300,
      "valorSegundoPremio": 1000,
      "tempoSegundoPremio": 7,
      "pontuacaoSegundoPremio": 1000
    },
    {
      "id": 4,
      "maiorPremioEstaNoBotaoDireito": true,
      "valorPremioImediato": 100,
      "pontuacaoPremioImediato": 100,
      "valorSegundoPremio": 1000,
      "tempoSegundoPremio": 30,
      "pontuacaoSegundoPremio": 1000
    },
    {
      "id": 5,
      "maiorPremioEstaNoBotaoDireito": false,
      "valorPremioImediato": 700,
      "pontuacaoPremioImediato": 700,
      "valorSegundoPremio": 1000,
      "tempoSegundoPremio": 15,
      "pontuacaoSegundoPremio": 1000
    },
    {
      "id": 6,
      "maiorPremioEstaNoBotaoDireito": false,
      "valorPremioImediato": 100,
      "pontuacaoPremioImediato": 100,
      "valorSegundoPremio": 1000,
      "tempoSegundoPremio": 7,
      "pontuacaoSegundoPremio": 1000
    },
    {
      "id": 7,
      "maiorPremioEstaNoBotaoDireito": true,
      "valorPremioImediato": 100,
      "pontuacaoPremioImediato": 100,
      "valorSegundoPremio": 1000,
      "tempoSegundoPremio": 60,
      "pontuacaoSegundoPremio": 1000
    },
    {
      "id": 8,
      "maiorPremioEstaNoBotaoDireito": true,
      "valorPremioImediato": 100,
      "pontuacaoPremioImediato": 100,
      "valorSegundoPremio": 1000,
      "tempoSegundoPremio": 7,
      "pontuacaoSegundoPremio": 1000
    },
    {
      "id": 9,
      "maiorPremioEstaNoBotaoDireito": false,
      "valorPremioImediato": 100,
      "pontuacaoPremioImediato": 100,
      "valorSegundoPremio": 1000,
      "tempoSegundoPremio": 15,
      "pontuacaoSegundoPremio": 1000
    },
    {
      "id": 10,
      "maiorPremioEstaNoBotaoDireito": false,
      "valorPremioImediato": 700,
      "pontuacaoPremioImediato": 700,
      "valorSegundoPremio": 1000,
      "tempoSegundoPremio": 30,
      "pontuacaoSegundoPremio": 1000
    },
    {
      "id": 11,
      "maiorPremioEstaNoBotaoDireito": true,
      "valorPremioImediato": 700,
      "pontuacaoPremioImediato": 700,
      "valorSegundoPremio": 1000,
      "tempoSegundoPremio": 7,
      "pontuacaoSegundoPremio": 1000
    },
    {
      "id": 12,
      "maiorPremioEstaNoBotaoDireito": true,
      "valorPremioImediato": 300,
      "pontuacaoPremioImediato": 300,
      "valorSegundoPremio": 1000,
      "tempoSegundoPremio": 15,
      "pontuacaoSegundoPremio": 1000
    }
  ]
}
